LICENSE.md
MANIFEST.in
README.rst
pyproject.toml
setup.cfg
setup.py
demo/alltoall.py
demo/broadcast.py
demo/collect.py
demo/fcollect.py
demo/hello.py
demo/lock.py
demo/lock_oo.py
demo/makefile
demo/pi.py
demo/ping.py
demo/race_winner.py
demo/race_winner_test.py
demo/rotget.py
demo/rotput.py
demo/api/addr.py
demo/api/hello.py
demo/api/lock.py
demo/api/makefile
demo/api/ping.py
demo/api/query.py
demo/api/rotget.py
demo/api/rotput.py
src/apicodegen.py
src/ffibuilder.py
src/fficompiler.py
src/libshmem.c
src/libshmem.h
src/libshmem/error.h
src/libshmem/fallback.h
src/libshmem/initfini.h
src/libshmem/memalloc.h
src/libshmem/compat/cray.h
src/libshmem/compat/openmpi.h
src/libshmem/compat/oshmpi.h
src/libshmem/compat/osss.h
src/libshmem/compat/sandia.h
src/libshmem/config/cray.h
src/libshmem/config/openmpi.h
src/libshmem/config/oshmpi.h
src/libshmem/config/osss.h
src/libshmem/config/sandia.h
src/shmem4py/__init__.py
src/shmem4py/__main__.py
src/shmem4py/api.pyi
src/shmem4py/py.typed
src/shmem4py/shmem.py
src/shmem4py.egg-info/PKG-INFO
src/shmem4py.egg-info/SOURCES.txt
src/shmem4py.egg-info/dependency_links.txt
src/shmem4py.egg-info/requires.txt
src/shmem4py.egg-info/top_level.txt
test/coverage.sh
test/test_alloc.py
test/test_amo.py
test/test_buf.py
test/test_coll.py
test/test_ctx.py
test/test_info.py
test/test_lock.py
test/test_prof.py
test/test_ptr.py
test/test_query.py
test/test_rc.py
test/test_reduce.py
test/test_rma.py
test/test_signal.py
test/test_sync.py
test/test_team.py