Metadata-Version: 2.1
Name: shmem4py
Version: 1.0.0
Summary: Python bindings for OpenSHMEM
Home-page: https://github.comm/mpi4py/shmem4py
Author: Lisandro Dalcin
Author-email: dalcinl@gmail.com
License: BSD-2-Clause
Requires-Python: >=3.7
License-File: LICENSE.md
